anyoneai/Untitled Project.py
anyoneai/__init__.py
anyoneai/labs.json
anyoneai/labs.py
anyoneai/static/android-chrome-192x192.png
anyoneai/static/android-chrome-512x512.png
anyoneai/static/apple-touch-icon.png
anyoneai/static/browserconfig.xml
anyoneai/static/color
anyoneai/static/demo.gif
anyoneai/static/favicon-16x16.png
anyoneai/static/favicon-32x32.png
anyoneai/static/favicon.ico
anyoneai/static/manifest.json
anyoneai/static/moonshot.png
anyoneai/static/moonshot_192.png
anyoneai/static/mstile-150x150.png
anyoneai/static/safari-pinned-tab.svg
anyoneai/static/sw.js
anyoneai/static/css/bootstrap.min.css
anyoneai/static/css/index.css
anyoneai/static/css/style.css
anyoneai/static/js/blockly_compressed.js
anyoneai/static/js/blockly_uncompressed.js
anyoneai/static/js/blocks_compressed.js
anyoneai/static/js/bluetooth.js
anyoneai/static/js/bootstrap.js
anyoneai/static/js/custom_blocks.js
anyoneai/static/js/custom_codegen.js
anyoneai/static/js/index.js
anyoneai/static/js/jquery.js
anyoneai/static/js/lab_list.js
anyoneai/static/js/popper.min.js
anyoneai/static/js/python_compressed.js
anyoneai/static/js/script.js
anyoneai/static/media/1x1.gif
anyoneai/static/media/click.mp3
anyoneai/static/media/click.ogg
anyoneai/static/media/click.wav
anyoneai/static/media/delete.mp3
anyoneai/static/media/delete.ogg
anyoneai/static/media/delete.wav
anyoneai/static/media/disconnect.mp3
anyoneai/static/media/disconnect.ogg
anyoneai/static/media/disconnect.wav
anyoneai/static/media/handclosed.cur
anyoneai/static/media/handdelete.cur
anyoneai/static/media/handopen.cur
anyoneai/static/media/quote0.png
anyoneai/static/media/quote1.png
anyoneai/static/media/sprites.png
anyoneai/static/media/sprites.svg
anyoneai/static/msg/messages.js
anyoneai/static/sample/Dancing Bot.mss
anyoneai/templates/404.html
anyoneai/templates/index.html
anyoneai/templates/lab.html
anyoneai/templates/lab_list.html
anyoneai-0.0.0.8.dist-info/LICENSE
anyoneai-0.0.0.8.dist-info/METADATA
anyoneai-0.0.0.8.dist-info/WHEEL
anyoneai-0.0.0.8.dist-info/entry_points.txt
anyoneai-0.0.0.8.dist-info/top_level.txt
anyoneai-0.0.0.8.dist-info/RECORD
