Metadata-Version: 2.1
Name: anyoneai
Version: 0.0.0.8
Summary: AnyoneAI aims to democratize AI education by providing an intuitive and interactive platform to gain a solid understanding of AI and learn how to solve problems with it. 
Home-page: https://github.com/ArjunInventor/anyoneai
Author: Arjun S
Author-email: arjun.santhoshkumar@gmail.com
License: GNU
Platform: UNKNOWN
Classifier: Development Status :: 3 - Alpha
Classifier: Programming Language :: Python :: 3
Classifier: Operating System :: OS Independent
Classifier: Intended Audience :: Education
Classifier: Intended Audience :: Developers
Classifier: Intended Audience :: Science/Research
Requires-Python: >=3.5
Requires-Dist: flask
Requires-Dist: gevent
